setup.py
nose_disabledoc/__init__.py
nose_disabledoc/plugin.py
nose_disabledoc.egg-info/PKG-INFO
nose_disabledoc.egg-info/SOURCES.txt
nose_disabledoc.egg-info/dependency_links.txt
nose_disabledoc.egg-info/entry_points.txt
nose_disabledoc.egg-info/requires.txt
nose_disabledoc.egg-info/top_level.txt