Metadata-Version: 1.1
Name: nose-disabledoc
Version: 1.0.2
Summary: Nose plugin that disables test docstrings in the verbose output and
Home-page: https://github.com/sanseihappa/nose-disabledoc
Author: Nat Williams, Kumar McMillan, Mark Hirota
Author-email: sanseihappa@users.noreply.github.com
License: Apache License
Platform: UNKNOWN
Classifier: Intended Audience :: Developers
Classifier: Natural Language :: English
Classifier: Operating System :: OS Independent
Classifier: Topic :: Software Development :: Testing
